sample_mcp_tests/__init__.py
sample_mcp_tests/__main__.py
sample_mcp_tests/mcp_tools.py
sample_mcp_tests-0.1.0.dist-info/METADATA
sample_mcp_tests-0.1.0.dist-info/WHEEL
sample_mcp_tests-0.1.0.dist-info/entry_points.txt
sample_mcp_tests-0.1.0.dist-info/RECORD
